pymordialblue/__init__.py
pymordialblue/android_app.py
pymordialblue/bin/tesseract/.gitignore
pymordialblue/bin/tesseract/ambiguous_words.1.html
pymordialblue/bin/tesseract/ambiguous_words.exe
pymordialblue/bin/tesseract/classifier_tester.1.html
pymordialblue/bin/tesseract/classifier_tester.exe
pymordialblue/bin/tesseract/cntraining.1.html
pymordialblue/bin/tesseract/cntraining.exe
pymordialblue/bin/tesseract/combine_lang_model.1.html
pymordialblue/bin/tesseract/combine_lang_model.exe
pymordialblue/bin/tesseract/combine_tessdata.1.html
pymordialblue/bin/tesseract/combine_tessdata.exe
pymordialblue/bin/tesseract/dawg2wordlist.1.html
pymordialblue/bin/tesseract/dawg2wordlist.exe
pymordialblue/bin/tesseract/libLerc.dll
pymordialblue/bin/tesseract/libarchive-13.dll
pymordialblue/bin/tesseract/libb2-1.dll
pymordialblue/bin/tesseract/libbrotlicommon.dll
pymordialblue/bin/tesseract/libbrotlidec.dll
pymordialblue/bin/tesseract/libbz2-1.dll
pymordialblue/bin/tesseract/libcairo-2.dll
pymordialblue/bin/tesseract/libcrypto-3-x64.dll
pymordialblue/bin/tesseract/libcurl-4.dll
pymordialblue/bin/tesseract/libdatrie-1.dll
pymordialblue/bin/tesseract/libdeflate.dll
pymordialblue/bin/tesseract/libexpat-1.dll
pymordialblue/bin/tesseract/libffi-8.dll
pymordialblue/bin/tesseract/libfontconfig-1.dll
pymordialblue/bin/tesseract/libfreetype-6.dll
pymordialblue/bin/tesseract/libfribidi-0.dll
pymordialblue/bin/tesseract/libgcc_s_seh-1.dll
pymordialblue/bin/tesseract/libgif-7.dll
pymordialblue/bin/tesseract/libgio-2.0-0.dll
pymordialblue/bin/tesseract/libglib-2.0-0.dll
pymordialblue/bin/tesseract/libgmodule-2.0-0.dll
pymordialblue/bin/tesseract/libgobject-2.0-0.dll
pymordialblue/bin/tesseract/libgraphite2.dll
pymordialblue/bin/tesseract/libharfbuzz-0.dll
pymordialblue/bin/tesseract/libiconv-2.dll
pymordialblue/bin/tesseract/libicudt75.dll
pymordialblue/bin/tesseract/libicuin75.dll
pymordialblue/bin/tesseract/libicuuc75.dll
pymordialblue/bin/tesseract/libidn2-0.dll
pymordialblue-0.1.1.dist-info/WHEEL
pymordialblue-0.1.1.dist-info/entry_points.txt
pymordialblue-0.1.1.dist-info/METADATA
pymordialblue-0.1.1.dist-info/RECORD
