Metadata-Version: 2.3
Name: pymordialblue
Version: 0.1.1
Summary: PymordialBlue: Advanced Android Automation for BlueStacks using Pymordial
Author: Malcom Godlike
Author-email: Malcom Godlike <ivmno1special@gmail.com>
Requires-Dist: adb-shell>=0.4.4
Requires-Dist: av>=16.1.0
Requires-Dist: numpy>=2.4.1
Requires-Dist: opencv-python-headless>=4.13.0.90
Requires-Dist: pillow>=12.1.0
Requires-Dist: psutil>=7.2.1
Requires-Dist: pymordial>=0.4.1
Requires-Dist: pytesseract>=0.3.13
Requires-Dist: pyyaml>=6.0.2
Requires-Python: >=3.13
